pythogic/__init__.py
pythogic/pythogic.py
pythogic/base/Alphabet.py
pythogic/base/FormalSystem.py
pythogic/base/Formula.py
pythogic/base/Symbol.py
pythogic/base/Symbols.py
pythogic/base/__init__.py
pythogic/base/utils.py
pythogic/fol/FOL.py
pythogic/fol/__init__.py
pythogic/fol/semantics/Assignment.py
pythogic/fol/semantics/Function.py
pythogic/fol/semantics/Interpretation.py
pythogic/fol/semantics/Object.py
pythogic/fol/semantics/Relation.py
pythogic/fol/semantics/__init__.py
pythogic/fol/syntax/FOLAlphabet.py
pythogic/fol/syntax/Term.py
pythogic/fol/syntax/__init__.py
pythogic/ldlf/LDLf.py
pythogic/ldlf/__init__.py
pythogic/ldlf_empty_traces/LDLf_EmptyTraces.py
pythogic/ldlf_empty_traces/__init__.py
pythogic/ltlf/LTLf.py
pythogic/ltlf/__init__.py
pythogic/ltlf/semantics/FiniteTrace.py
pythogic/ltlf/semantics/__init__.py
pythogic/pl/PL.py
pythogic/pl/__init__.py
pythogic/pl/semantics/PLInterpretation.py
pythogic/pl/semantics/__init__.py
pythogic/ref/REf.py
pythogic/ref/__init__.py
pythogic-0.2.8.dist-info/DESCRIPTION.rst
pythogic-0.2.8.dist-info/METADATA
pythogic-0.2.8.dist-info/RECORD
pythogic-0.2.8.dist-info/WHEEL
pythogic-0.2.8.dist-info/metadata.json
pythogic-0.2.8.dist-info/top_level.txt
