Metadata-Version: 2.0
Name: pythogic
Version: 0.2.8
Summary: Python package for deal with logical formulas and formal systems
Home-page: https://github.com/MarcoFavorito/pythogic
Author: Marco Favorito
Author-email: marco.favorito@gmail.com
License: MIT license
Keywords: pythogic
Platform: UNKNOWN
Classifier: Development Status :: 2 - Pre-Alpha
Classifier: Intended Audience :: Developers
Classifier: License :: OSI Approved :: MIT License
Classifier: Natural Language :: English
Classifier: Programming Language :: Python :: 3
Classifier: Programming Language :: Python :: 3.5
Classifier: Programming Language :: Python :: 3.6
